README.md
setup.py
ODToolkit/Analysis.py
ODToolkit/Augmentation.py
ODToolkit/DataCleaning.py
ODToolkit/Dataset.py
ODToolkit/Transformation.py
ODToolkit/Visualization.py
ODToolkit/__init__.py
ODToolkit/_utils.py
ODToolkit.egg-info/PKG-INFO
ODToolkit.egg-info/SOURCES.txt
ODToolkit.egg-info/dependency_links.txt
ODToolkit.egg-info/requires.txt
ODToolkit.egg-info/top_level.txt