Metadata-Version: 2.1
Name: ODToolkit
Version: 0.0.10
Summary: An object detection toolkit for data mining and visualization
Home-page: https://github.com/BarCodeReader/ODToolkit
Author: YUN_Yi_Ke
Author-email: assassin@gs-roobt.com
License: UNKNOWN
Platform: UNKNOWN
Requires-Python: >=3.6
